{
  "heroName": "Reina",
  "versionA": "cbt-phase-1",
  "versionB": "ccbt",
  "generatedAt": "2026-05-08T11:43:35.414Z",
  "skills": {
    "1": {
      "hasChanges": true,
      "description": {
        "unified": "Quickly stabs the enemy, dealing Physical Damage. On critical hit, applies [Wound] 1 stack and resets the cooldown. For each [Wound] stack, this skill's damage is increased by 20%, and [(added) you are immune to all damage while casting]."
      }
    },
    "2": {
      "hasChanges": true,
      "mana_cost": {
        "from": "3",
        "to": "2"
      },
      "description": {
        "unified": "Removes your harmful effects and increases Attack by 205(1+0.3Skill Level) and Critical Hit Chance by [500->600] for [15sec->10 sec]."
      }
    },
    "3": {
      "hasChanges": true,
      "mana_cost": {
        "from": "4",
        "to": "3"
      },
      "description": {
        "unified": "Performs a series of attacks, dealing Physical Damage 9 times, then finishes with a powerful thrust that deals Physical Damage and knocks the enemy far away. [(removed) The damage of this skill is increased by 20% per [Wound] stack, and all [Wound] stacks are consumed on the final hit.]"
      }
    },
    "4": {
      "hasChanges": true,
      "description": {
        "unified": "On critical hit, increases Attack by 40(1+0.3*Skill Level) for 10 sec. This effect stacks up to 8 times."
      }
    }
  },
  "books": {},
  "perks_t3": {
    "1": {
      "hasChanges": true,
      "light": {
        "unified": "Mana cost is increased by 1000, but the maximum number of [Wound Stacks] is increased to 10. If [Wound Stacks] is 10, deals additional damage equal to [(added) 150%] of Attack Power."
      }
    },
    "2": {
      "hasChanges": true,
      "dark": {
        "unified": "Mana cost is increased by 1000, but the Critical Hit Chance increase effect is changed to increase Critical Damage by [65%->120%], and damage dealt to bosses is increased by 30%."
      }
    },
    "4": {
      "hasChanges": true,
      "dark": {
        "unified": "If there are [(added) 5 or more] stacks, all damage taken is reduced by [(added) 20%]. [(removed) Gain 45 Physical Dodge per stack.]"
      }
    }
  },
  "uts": {
    "3": {
      "name": "Medal of Swiftness",
      "hasChanges": true,
      "description": {
        "unified": "[Shooting Star] Increases DMG by {0}% and [(added) upon a Crit Hit, recovers Mana by 200]. [(removed) adds 1 Wound per attack.]"
      },
      "values": {
        "0": {
          "from": "25 / 30 / 35 / 40 / 45 / 50",
          "to": "20 / 24 / 29 / 35 / 42 / 50"
        }
      }
    }
  },
  "perks_t5": {
    "hasChanges": true,
    "dark": {
      "unified": "When using a skill, has a 10% chance to increase your Critical Damage by [7%->10%]. This effect stacks up to 10 times."
    }
  },
  "uw": {
    "hasChanges": true,
    "description": {
      "unified": "Each time a critical hit occurs, for 15 sec your Attack Speed is increased by {0} and Critical Damage is increased by {1}%. This effect stacks up to [8->5] times."
    },
    "values": {
      "0": {
        "from": "3 / 3.6 / 4.2 / 4.8 / 5.4 / 6",
        "to": "80 / 90 / 110 / 130 / 160 / 200"
      },
      "1": {
        "from": "6 / 7.2 / 8.4 / 9.6 / 10.8 / 12",
        "to": "20 / 24 / 29 / 35 / 42 / 50"
      }
    }
  }
}